__init__.py
tushare_models/__init__.py
tushare_models/adj_factor.py
tushare_models/anns_d.py
tushare_models/bak_basic.py
tushare_models/bak_daily.py
tushare_models/balancesheet.py
tushare_models/bc_bestotcqt.py
tushare_models/bc_otcqt.py
tushare_models/bishijie.py
tushare_models/block_trade.py
tushare_models/bo_cinema.py
tushare_models/bo_daily.py
tushare_models/bo_monthly.py
tushare_models/bo_weekly.py
tushare_models/bond_blk.py
tushare_models/bond_blk_detail.py
tushare_models/broker_recommend.py
tushare_models/bse_mapping.py
tushare_models/btc8.py
tushare_models/btc_marketcap.py
tushare_models/btc_pricevol.py
tushare_models/cashflow.py
tushare_models/cb_basic.py
tushare_models/cb_call.py
tushare_models/cb_daily.py
tushare_models/cb_factor_pro.py
tushare_models/cb_issue.py
tushare_models/cb_price_chg.py
tushare_models/cb_rate.py
tushare_models/cb_share.py
tushare_models/ccass_hold.py
tushare_models/ccass_hold_detail.py
tushare_models/cctv_news.py
tushare_models/ci_daily.py
tushare_models/ci_index_member.py
tushare_models/cn_cpi.py
tushare_models/cn_gdp.py
tushare_models/cn_m.py
tushare_models/cn_pmi.py
tushare_models/cn_ppi.py
tushare_models/coin_bar.py
tushare_models/coin_pair.py
tushare_models/coincap.py
tushare_models/coinexchanges.py
tushare_models/coinfees.py
tushare_models/coinlist.py
tushare_models/coinpair.py
tushare_models/cyq_chips.py
tushare_models/cyq_perf.py
tushare_models/daily.py
tushare_models/daily_basic.py
tushare_models/daily_info.py
tushare_models/dc_daily.py
tushare_models/dc_hot.py
tushare_models/dc_index.py
tushare_models/dc_member.py
tushare_models/disclosure_date.py
tushare_models/dividend.py
tushare_models/eco_cal.py
tushare_models/etf_basic.py
tushare_models/etf_index.py
tushare_models/exchange_ann.py
tushare_models/exchange_twitter.py
tushare_models/express.py
tushare_models/film_record.py
tushare_models/fina_audit.py
tushare_models/fina_indicator.py
tushare_models/fina_mainbz.py
tushare_models/forecast.py
tushare_models/ft_limit.py
tushare_models-0.1.1.dist-info/licenses/LICENSE
tushare_models-0.1.1.dist-info/METADATA
tushare_models-0.1.1.dist-info/WHEEL
tushare_models-0.1.1.dist-info/top_level.txt
tushare_models-0.1.1.dist-info/RECORD
