Metadata-Version: 2.4
Name: tushare-models
Version: 0.1.1
Summary: Tushare SQLAlchemy Models
Author-email: zhangbingchen <1731259685@qq.com>
License: MIT
Classifier: Programming Language :: Python :: 3
Classifier: License :: OSI Approved :: MIT License
Classifier: Operating System :: OS Independent
Requires-Python: >=3.11
License-File: LICENSE
Requires-Dist: sqlalchemy>=2.0.38
Provides-Extra: clickhouse
Requires-Dist: clickhouse-sqlalchemy>=0.3.2; extra == "clickhouse"
Provides-Extra: starrocks
Requires-Dist: starrocks>=1.2.1; extra == "starrocks"
Provides-Extra: databend
Requires-Dist: databend-sqlalchemy>=0.5.0; extra == "databend"
Provides-Extra: all
Requires-Dist: clickhouse-sqlalchemy>=0.3.2; extra == "all"
Requires-Dist: starrocks>=1.2.1; extra == "all"
Requires-Dist: databend-sqlalchemy>=0.5.0; extra == "all"
Dynamic: license-file
